flaskify.py
flaskify-0.2.dist-info/DESCRIPTION.rst
flaskify-0.2.dist-info/METADATA
flaskify-0.2.dist-info/RECORD
flaskify-0.2.dist-info/WHEEL
flaskify-0.2.dist-info/entry_points.txt
flaskify-0.2.dist-info/metadata.json
flaskify-0.2.dist-info/top_level.txt
