Metadata-Version: 2.0
Name: flaskify
Version: 0.2
Summary: Simple Flask project generation
Home-page: UNKNOWN
Author: Kenny Brawner
Author-email: kjbrawner@crimson.ua.edu
License: UNKNOWN
Platform: UNKNOWN
Requires-Dist: Click
